pygerber/__init__.py
pygerber/__main__.py
pygerber/backend/__init__.py
pygerber/backend/abstract/__init__.py
pygerber/backend/abstract/aperture_handle.py
pygerber/backend/abstract/backend_cls.py
pygerber/backend/abstract/draw_commands/__init__.py
pygerber/backend/abstract/draw_commands/draw_arc.py
pygerber/backend/abstract/draw_commands/draw_bounding_box.py
pygerber/backend/abstract/draw_commands/draw_circle.py
pygerber/backend/abstract/draw_commands/draw_command.py
pygerber/backend/abstract/draw_commands/draw_paste.py
pygerber/backend/abstract/draw_commands/draw_polygon.py
pygerber/backend/abstract/draw_commands/draw_rectangle.py
pygerber/backend/abstract/draw_commands/draw_region.py
pygerber/backend/abstract/draw_commands/draw_vector_line.py
pygerber/backend/abstract/draw_commands_handle.py
pygerber/backend/abstract/drawing_target.py
pygerber/backend/abstract/errors.py
pygerber/backend/abstract/result_handle.py
pygerber/backend/rasterized_2d/__init__.py
pygerber/backend/rasterized_2d/aperture_handle.py
pygerber/backend/rasterized_2d/backend_cls.py
pygerber/backend/rasterized_2d/color_scheme.py
pygerber/backend/rasterized_2d/draw_commands/__init__.py
pygerber/backend/rasterized_2d/draw_commands/draw_arc.py
pygerber/backend/rasterized_2d/draw_commands/draw_bounding_box.py
pygerber/backend/rasterized_2d/draw_commands/draw_circle.py
pygerber/backend/rasterized_2d/draw_commands/draw_paste.py
pygerber/backend/rasterized_2d/draw_commands/draw_polygon.py
pygerber/backend/rasterized_2d/draw_commands/draw_rectangle.py
pygerber/backend/rasterized_2d/draw_commands/draw_region.py
pygerber/backend/rasterized_2d/draw_commands/draw_vector_line.py
pygerber/backend/rasterized_2d/draw_commands_handle.py
pygerber/backend/rasterized_2d/drawing_target.py
pygerber/backend/rasterized_2d/errors.py
pygerber/backend/rasterized_2d/image_tools.py
pygerber/backend/rasterized_2d/result_handle.py
pygerber/common/__init__.py
pygerber/common/error.py
pygerber/common/frozen_general_model.py
pygerber-2.4.3.dist-info/LICENSE.md
pygerber-2.4.3.dist-info/METADATA
pygerber-2.4.3.dist-info/WHEEL
pygerber-2.4.3.dist-info/entry_points.txt
pygerber-2.4.3.dist-info/RECORD
