Metadata-Version: 2.1
Name: pygerber
Version: 2.4.3
Summary: Parsing and rendering toolkit for Gerber X3 file format
Home-page: https://github.com/Argmaster/pygerber
License: MIT
Keywords: gerber,pcb,embedded,images,x3
Author: Krzysztof Wisniewski
Author-email: argmaster.world@gmail.com
Requires-Python: >=3.8,<4.0
Classifier: Development Status :: 5 - Production/Stable
Classifier: Environment :: Console
Classifier: Intended Audience :: Developers
Classifier: Intended Audience :: End Users/Desktop
Classifier: Intended Audience :: Information Technology
Classifier: Intended Audience :: Manufacturing
Classifier: Intended Audience :: Science/Research
Classifier: License :: OSI Approved :: MIT License
Classifier: Operating System :: MacOS
Classifier: Operating System :: Microsoft :: Windows
Classifier: Operating System :: OS Independent
Classifier: Operating System :: POSIX :: Linux
Classifier: Programming Language :: Python
Classifier: Programming Language :: Python :: 3
Classifier: Programming Language :: Python :: 3.8
Classifier: Programming Language :: Python :: 3.9
Classifier: Programming Language :: Python :: 3.10
Classifier: Programming Language :: Python :: 3.11
Classifier: Programming Language :: Python :: 3 :: Only
Classifier: Programming Language :: Python :: 3.12
Classifier: Programming Language :: Python :: 3.13
Classifier: Programming Language :: Python :: Implementation :: CPython
Classifier: Programming Language :: Python :: Implementation :: PyPy
Classifier: Topic :: File Formats
Classifier: Topic :: Multimedia
Classifier: Topic :: Multimedia :: Graphics
Classifier: Topic :: Multimedia :: Graphics :: Presentation
Classifier: Topic :: Multimedia :: Graphics :: Viewers
Classifier: Topic :: Printing
Classifier: Topic :: Scientific/Engineering :: Visualization
Classifier: Topic :: Software Development :: Embedded Systems
Classifier: Topic :: Utilities
Classifier: Typing :: Typed
Provides-Extra: all
Provides-Extra: language-server
Provides-Extra: svg
Requires-Dist: click (>=8.0.0) ; python_version >= "3.8"
Requires-Dist: drawsvg (>=2.3.0,<3.0.0) ; extra == "svg" or extra == "all"
Requires-Dist: lsprotocol (>=2023.0.0a3,<2024.0.0) ; extra == "language-server" or extra == "all"
Requires-Dist: numpy (<1.25) ; python_version >= "3.8" and python_version < "3.9"
Requires-Dist: numpy (<2.1) ; python_version >= "3.9" and python_version < "3.10"
Requires-Dist: numpy (<3) ; python_version >= "3.10"
Requires-Dist: pillow (>=8.0.0) ; python_version >= "3.9"
Requires-Dist: pillow (>=8.0.0,<11.0.0) ; python_version >= "3.8" and python_version < "3.9"
Requires-Dist: pydantic (>=2.0.0) ; python_version >= "3.8"
Requires-Dist: pygls (>=1.0.2,<2.0.0) ; extra == "language-server" or extra == "all"
Requires-Dist: pyparsing (>=3.0.0) ; python_version >= "3.9"
Requires-Dist: pyparsing (>=3.0.0,<3.2.0) ; python_version >= "3.8" and python_version < "3.9"
Project-URL: Documentation, https://argmaster.github.io/pygerber/stable
Project-URL: Repository, https://github.com/Argmaster/pygerber
